pv_visualizer/__init__.py
pv_visualizer/app/__init__.py
pv_visualizer/app/jupyter.py
pv_visualizer/app/main.py
pv_visualizer/app/assets/__init__.py
pv_visualizer/app/assets/database-remove-outline.svg
pv_visualizer/app/assets/pv_logo.svg
pv_visualizer/app/engine/__init__.py
pv_visualizer/app/engine/proxymanager/__init__.py
pv_visualizer/app/engine/proxymanager/const.py
pv_visualizer/app/engine/proxymanager/core.py
pv_visualizer/app/engine/proxymanager/data_informations.py
pv_visualizer/app/engine/proxymanager/decorators.py
pv_visualizer/app/engine/proxymanager/definitions.py
pv_visualizer/app/engine/proxymanager/domain_helpers.py
pv_visualizer/app/engine/proxymanager/domains.py
pv_visualizer/app/engine/proxymanager/paraview.py
pv_visualizer/app/engine/reactions/__init__.py
pv_visualizer/app/engine/reactions/camera.py
pv_visualizer/app/engine/reactions/representation.py
pv_visualizer/app/engine/reactions/scalar_range.py
pv_visualizer/app/ui/__init__.py
pv_visualizer/app/ui/algorithms.py
pv_visualizer/app/ui/files.py
pv_visualizer/app/ui/main.py
pv_visualizer/app/ui/pipeline.py
pv_visualizer/app/ui/settings.py
pv_visualizer/app/ui/state_change.py
pv_visualizer/app/ui/view_toolbox.py
pv_visualizer/html/__init__.py
pv_visualizer/html/data_information.py
pv_visualizer/html/file_browser.py
pv_visualizer/html/filters.py
pv_visualizer/html/pipeline.py
pv_visualizer/html/proxy_editor.py
pv_visualizer/html/module/__init__.py
pv_visualizer/html/module/serve/demo.html
pv_visualizer/html/module/serve/vue-pv_visualizer.common.js
pv_visualizer/html/module/serve/vue-pv_visualizer.common.js.map
pv_visualizer/html/module/serve/vue-pv_visualizer.umd.js
pv_visualizer/html/module/serve/vue-pv_visualizer.umd.js.map
pv_visualizer/html/module/serve/vue-pv_visualizer.umd.min.js
pv_visualizer/html/module/serve/vue-pv_visualizer.umd.min.js.map
pv_visualizer-0.1.6.dist-info/LICENSE
pv_visualizer-0.1.6.dist-info/METADATA
pv_visualizer-0.1.6.dist-info/WHEEL
pv_visualizer-0.1.6.dist-info/entry_points.txt
pv_visualizer-0.1.6.dist-info/top_level.txt
pv_visualizer-0.1.6.dist-info/RECORD
