Metadata-Version: 2.1
Name: pv-visualizer
Version: 0.1.6
Summary: Web frontend to ParaView
Author: Kitware Inc.
License: BSD License
Keywords: Python,Interactive,Web,Application,Framework
Classifier: Development Status :: 1 - Planning
Classifier: Environment :: Web Environment
Classifier: License :: OSI Approved :: BSD License
Classifier: Natural Language :: English
Classifier: Operating System :: OS Independent
Classifier: Programming Language :: Python :: 3 :: Only
Classifier: Programming Language :: JavaScript
Classifier: Topic :: Software Development :: Libraries :: Application Frameworks
Classifier: Topic :: Software Development :: Libraries :: Python Modules
License-File: LICENSE
Requires-Dist: trame
Requires-Dist: trame-vuetify
Requires-Dist: trame-components
Requires-Dist: trame-vtk
Requires-Dist: trame-simput
